varstardetect/Star.py
varstardetect/__init__.py
varstardetect/Targets/sector_1.csv
varstardetect-1.1.10.dist-info/LICENSE.txt
varstardetect-1.1.10.dist-info/METADATA
varstardetect-1.1.10.dist-info/WHEEL
varstardetect-1.1.10.dist-info/top_level.txt
varstardetect-1.1.10.dist-info/RECORD
