Metadata-Version: 2.1
Name: varstardetect
Version: 1.1.10
Summary: TESS Variable Star Light Curve Fitter
Home-page: https://github.com/VarStarDetect/varstardetect
Author: Nicolas Carrizosa Arias, Jorge Perez Gonzalez and Andres Cadenas Blanco
Author-email: varstardetect@gmail.com
License: gpl-3.0
Keywords: Star,Astronomy,Star Detection,Detection
Platform: UNKNOWN
Classifier: Programming Language :: Python :: 3
Classifier: Framework :: Matplotlib
Classifier: Topic :: Scientific/Engineering :: Mathematics
Classifier: Topic :: Scientific/Engineering :: Astronomy
Classifier: License :: OSI Approved :: GNU General Public License v3 (GPLv3)
Classifier: Development Status :: 4 - Beta
Classifier: Intended Audience :: Science/Research
Classifier: Operating System :: OS Independent
Requires-Python: >=3.8
License-File: LICENSE.txt
Requires-Dist: numpy
Requires-Dist: matplotlib
Requires-Dist: astropy
Requires-Dist: pandas
Requires-Dist: lightkurve
